[
    {
        "id": "blk_contact_primary",
        "page_key": "contact",
        "type": "contact_info",
        "name": "Contato principal",
        "eyebrow": "Canal oficial",
        "title": "Contato",
        "body": "Quer saber mais ou colaborar com o CEPIN-CIS? Entre em contato com nossa equipe de pesquisa.",
        "items": [
            {
                "label": "Email institucional",
                "value": "cepin.cis@ifspcaraguatatuba.edu.br",
                "url": "mailto:cepin.cis@ifspcaraguatatuba.edu.br"
            },
            {
                "label": "Endereco",
                "value": "IFSP Campus Caraguatatuba, sala 107B.",
                "url": ""
            }
        ],
        "cta_label": "Enviar e-mail",
        "cta_url": "mailto:cepin.cis@ifspcaraguatatuba.edu.br",
        "embed_url": "",
        "width": "half",
        "position": 10,
        "status": "published",
        "show_context_note": true,
        "created_at": "2026-04-15 00:00:00",
        "updated_at": "2026-04-15 00:00:00"
    },
    {
        "id": "blk_contact_map",
        "page_key": "contact",
        "type": "map_embed",
        "name": "Mapa do campus",
        "eyebrow": "",
        "title": "Mapa",
        "body": "",
        "items": [],
        "cta_label": "",
        "cta_url": "",
        "embed_url": "https://www.google.com/maps/embed?pb=!1m14!1m12!1m3!1d228.4439040435433!2d-45.4258447087537!3d-23.636501255140573!2m3!1f0!2f0!3f0!3m2!1i1024!2i768!4f13.1!5e0!3m2!1spt-BR!2sbr!4v1763413745838!5m2!1spt-BR!2sbr",
        "width": "half",
        "position": 20,
        "status": "published",
        "show_context_note": false,
        "created_at": "2026-04-15 00:00:00",
        "updated_at": "2026-04-15 00:00:00"
    },
    {
        "id": "blk_thematic_intro",
        "page_key": "thematic_areas",
        "type": "thematic_intro",
        "name": "Intro Areas Tematicas",
        "eyebrow": "CEPIN-CIS",
        "title": "Areas tematicas",
        "body": "As Areas Tematicas nas quais serao alinhadas as linhas de pesquisa foram definidas para orientar as atividades do CEPIN-CIS e compreendem:",
        "items": [],
        "cta_label": "",
        "cta_url": "",
        "embed_url": "",
        "width": "full",
        "position": 10,
        "status": "published",
        "show_context_note": false,
        "created_at": "2026-04-22 00:00:00",
        "updated_at": "2026-04-22 00:00:00"
    },
    {
        "id": "blk_thematic_educis",
        "page_key": "thematic_areas",
        "type": "thematic_topic",
        "name": "Area Tematica EduCIS",
        "eyebrow": "EduCIS",
        "title": "Formacao de recursos humanos para cidades inteligentes e sustentaveis",
        "body": "Desenvolvimento de recursos humanos e metodos ageis de capacitacao para impulsionar a inovacao em Cidades Inteligentes e Sustentaveis.",
        "items": [],
        "cta_label": "",
        "cta_url": "",
        "embed_url": "",
        "width": "half",
        "position": 20,
        "status": "published",
        "show_context_note": false,
        "created_at": "2026-04-22 00:00:00",
        "updated_at": "2026-04-22 00:00:00"
    },
    {
        "id": "blk_thematic_ecomat",
        "page_key": "thematic_areas",
        "type": "thematic_topic",
        "name": "Area Tematica EcoMat",
        "eyebrow": "EcoMat",
        "title": "Novos materiais e economia circular",
        "body": "Investigar materiais sustentaveis e promover economia circular, reduzindo o impacto ambiental.",
        "items": [],
        "cta_label": "",
        "cta_url": "",
        "embed_url": "",
        "width": "half",
        "position": 30,
        "status": "published",
        "show_context_note": false,
        "created_at": "2026-04-22 00:00:00",
        "updated_at": "2026-04-22 00:00:00"
    },
    {
        "id": "blk_thematic_iot",
        "page_key": "thematic_areas",
        "type": "thematic_topic",
        "name": "Area Tematica IoT",
        "eyebrow": "IoT",
        "title": "Desenvolvimento tecnologico e conectividade para cidades inteligentes e sustentaveis",
        "body": "Desenvolver tecnologias avancadas e solucoes de conectividade para criar ambientes urbanos mais inteligentes, eficientes e sustentaveis.",
        "items": [],
        "cta_label": "",
        "cta_url": "",
        "embed_url": "",
        "width": "half",
        "position": 40,
        "status": "published",
        "show_context_note": false,
        "created_at": "2026-04-22 00:00:00",
        "updated_at": "2026-04-22 00:00:00"
    },
    {
        "id": "blk_thematic_carbonzero",
        "page_key": "thematic_areas",
        "type": "thematic_topic",
        "name": "Area Tematica CarbonZero",
        "eyebrow": "CarbonZero",
        "title": "Descarbonizacao do ambiente construido",
        "body": "Promover a reducao das emissoes de carbono em edificios, infraestrutura, mobilidade urbana, fontes de energia e saneamento ambiental.",
        "items": [],
        "cta_label": "",
        "cta_url": "",
        "embed_url": "",
        "width": "half",
        "position": 50,
        "status": "published",
        "show_context_note": false,
        "created_at": "2026-04-22 00:00:00",
        "updated_at": "2026-04-22 00:00:00"
    },
    {
        "id": "blk_thematic_urbansmart",
        "page_key": "thematic_areas",
        "type": "thematic_topic",
        "name": "Area Tematica UrbanSmart",
        "eyebrow": "UrbanSmart",
        "title": "Monitoramento e operacoes urbanas inteligentes",
        "body": "Desenvolver solucoes para monitorar e gerenciar a infraestrutura urbana com gemeos digitais, plataformas digitais, sistemas autonomos e drones, ampliando a resiliencia climatica.",
        "items": [],
        "cta_label": "",
        "cta_url": "",
        "embed_url": "",
        "width": "half",
        "position": 60,
        "status": "published",
        "show_context_note": false,
        "created_at": "2026-04-22 00:00:00",
        "updated_at": "2026-04-22 00:00:00"
    },
    {
        "id": "blk_thematic_regulation",
        "page_key": "thematic_areas",
        "type": "thematic_cta",
        "name": "Regulamento CEPIN-CIS",
        "eyebrow": "",
        "title": "Regulamento",
        "body": "O regulamento do Centro de Pesquisa e Inovacao em Cidades Inteligentes e Sustentaveis (CEPIN-CIS) foi aprovado em 2024 pelo Conselho de Campus (CONCAM) do IFSP Caraguatatuba. Este marco normativo consolida a missao do CEPIN-CIS como espaco de fomento a pesquisa aplicada, a inovacao tecnologica e a reflexao critica sobre os desafios contemporaneos das cidades.\n\nO regulamento estabelece as diretrizes para a participacao de servidores e discentes vinculados a projetos de ensino, pesquisa ou extensao que dialoguem com as areas tematicas do Centro, alem de abrir espaco para a colaboracao de pesquisadores externos.",
        "items": [],
        "cta_label": "Clique aqui para ver o regulamento",
        "cta_url": "https://www.ifspcaraguatatuba.edu.br/images/CEPIN/Portaria_Normativa_n%C2%BA_14-2024_Aprova_regulamento_CEPIN-CIS.pdf",
        "embed_url": "",
        "width": "half",
        "position": 70,
        "status": "published",
        "show_context_note": false,
        "created_at": "2026-04-22 00:00:00",
        "updated_at": "2026-04-22 00:00:00"
    },
    {
        "id": "blk_thematic_contact",
        "page_key": "thematic_areas",
        "type": "thematic_cta",
        "name": "Contato Areas Tematicas",
        "eyebrow": "",
        "title": "Contato",
        "body": "Quer saber mais ou colaborar com o CEPIN-CIS? Entre em contato com nossa equipe de pesquisa.",
        "items": [
            {
                "label": "Email institucional",
                "value": "cepin.cis@ifspcaraguatatuba.edu.br",
                "url": "mailto:cepin.cis@ifspcaraguatatuba.edu.br"
            }
        ],
        "cta_label": "Enviar E-mail",
        "cta_url": "./contact.php",
        "embed_url": "",
        "width": "half",
        "position": 80,
        "status": "published",
        "show_context_note": false,
        "created_at": "2026-04-22 00:00:00",
        "updated_at": "2026-04-22 00:00:00"
    },
    {
        "id": "blk_about_intro",
        "page_key": "about",
        "type": "about_text",
        "name": "Sobre CEPIN-CIS",
        "eyebrow": "CEPIN-CIS",
        "title": "Sobre nos",
        "body": "O Centro de Pesquisa e Inovacao em Cidades Inteligentes e Sustentaveis (CEPIN-CIS), implementado no IFSP campus Caraguatatuba, tem como missao fomentar o desenvolvimento de cidades inteligentes e sustentaveis. Para isso, atua como um repositorio de tecnologias, um espaco dedicado a experimentacao pratica e um agente de interlocucao capaz de estabelecer conexoes produtivas entre os setores publico e privado.\n\nSua atuacao se estrutura de maneira a promover, de forma inclusiva, colaborativa e equitativa, o debate e a construcao de solucoes que contemplem as dimensoes ambientais, economicas, sociais e culturais da sustentabilidade.\n\nNesse sentido, o CEPIN-CIS direciona seus esforcos para desenvolver investigacao fundamental ou aplicada voltada ao campo das cidades inteligentes e sustentaveis, aproximando pesquisa, transferencia de tecnologia e aplicacao pratica.",
        "items": [],
        "cta_label": "",
        "cta_url": "",
        "embed_url": "",
        "media_url": "",
        "media_dark_url": "",
        "media_alt": "",
        "width": "span_2",
        "height": "tall",
        "position": 10,
        "status": "published",
        "show_context_note": false,
        "created_at": "2026-04-22 00:00:00",
        "updated_at": "2026-04-22 00:00:00"
    },
    {
        "id": "blk_about_banner",
        "page_key": "about",
        "type": "about_media",
        "name": "Banner institucional",
        "eyebrow": "",
        "title": "",
        "body": "",
        "items": [],
        "cta_label": "",
        "cta_url": "",
        "embed_url": "",
        "media_url": "./img/banner.png",
        "media_dark_url": "./img/bannerescuro.png",
        "media_alt": "Logo CEPIN-CIS",
        "width": "span_2",
        "height": "tall",
        "position": 20,
        "status": "published",
        "show_context_note": false,
        "created_at": "2026-04-22 00:00:00",
        "updated_at": "2026-04-22 00:00:00"
    },
    {
        "id": "blk_about_infrastructure",
        "page_key": "about",
        "type": "about_list",
        "name": "Infraestruturas",
        "eyebrow": "Estrutura",
        "title": "Infraestruturas",
        "body": "O CEPIN-CIS esta localizado na sala 107B do IFSP Campus Caraguatatuba, e sua infraestrutura conta com os seguintes recursos:",
        "items": [
            {
                "label": "",
                "value": "03 Desktop HP 280 G5 SFF com processador Intel Core i7 de 10a geracao, SSD 512 GB e 16 GB de RAM.",
                "url": ""
            },
            {
                "label": "",
                "value": "03 monitores LG 23.8 Full HD 75Hz 5ms HDMI.",
                "url": ""
            },
            {
                "label": "",
                "value": "01 notebook VAIO FE15 AMD Ryzen 7 com Windows 11, 16 GB e SSD 512 GB.",
                "url": ""
            },
            {
                "label": "",
                "value": "01 switch TP-Link 8 portas TL-SG108E.",
                "url": ""
            },
            {
                "label": "",
                "value": "07 kits Arduino com sensores, display, motores e placa Mega 2560 R3.",
                "url": ""
            },
            {
                "label": "",
                "value": "01 kit de sensores diversos compativeis com Arduino.",
                "url": ""
            }
        ],
        "cta_label": "",
        "cta_url": "",
        "embed_url": "",
        "media_url": "./img/Monitor.png",
        "media_dark_url": "",
        "media_alt": "Monitor ilustrando a infraestrutura do CEPIN-CIS",
        "width": "full",
        "height": "regular",
        "position": 30,
        "status": "published",
        "show_context_note": false,
        "created_at": "2026-04-22 00:00:00",
        "updated_at": "2026-04-22 00:00:00"
    },
    {
        "id": "blk_about_regulation",
        "page_key": "about",
        "type": "about_cta",
        "name": "Regulamento sobre",
        "eyebrow": "",
        "title": "Regulamento",
        "body": "O regulamento do Centro de Pesquisa e Inovacao em Cidades Inteligentes e Sustentaveis (CEPIN-CIS) foi aprovado em 2024 pelo Conselho de Campus (CONCAM) do IFSP Caraguatatuba. Este marco normativo consolida a missao do CEPIN-CIS como espaco de fomento a pesquisa aplicada, a inovacao tecnologica e a reflexao critica sobre os desafios contemporaneos das cidades.\n\nO regulamento estabelece as diretrizes para a participacao de servidores e discentes vinculados a projetos de ensino, pesquisa ou extensao que dialoguem com as areas tematicas do Centro, alem de abrir espaco para a colaboracao de pesquisadores externos.",
        "items": [],
        "cta_label": "Clique aqui para ver o regulamento",
        "cta_url": "https://www.ifspcaraguatatuba.edu.br/images/CEPIN/Portaria_Normativa_n%C2%BA_14-2024_Aprova_regulamento_CEPIN-CIS.pdf",
        "embed_url": "",
        "media_url": "",
        "media_dark_url": "",
        "media_alt": "",
        "width": "span_2",
        "height": "regular",
        "position": 40,
        "status": "published",
        "show_context_note": false,
        "created_at": "2026-04-22 00:00:00",
        "updated_at": "2026-04-22 00:00:00"
    },
    {
        "id": "blk_about_contact",
        "page_key": "about",
        "type": "about_cta",
        "name": "Contato sobre",
        "eyebrow": "",
        "title": "Contato",
        "body": "Quer saber mais ou colaborar com o CEPIN-CIS? Entre em contato com nossa equipe de pesquisa.",
        "items": [
            {
                "label": "Email institucional",
                "value": "cepin.cis@ifspcaraguatatuba.edu.br",
                "url": "mailto:cepin.cis@ifspcaraguatatuba.edu.br"
            },
            {
                "label": "Endereco",
                "value": "IFSP Campus Caraguatatuba, sala 107B.",
                "url": ""
            }
        ],
        "cta_label": "Enviar E-mail",
        "cta_url": "mailto:cepin.cis@ifspcaraguatatuba.edu.br",
        "embed_url": "",
        "media_url": "",
        "media_dark_url": "",
        "media_alt": "",
        "width": "span_2",
        "height": "regular",
        "position": 50,
        "status": "published",
        "show_context_note": false,
        "created_at": "2026-04-22 00:00:00",
        "updated_at": "2026-04-22 00:00:00"
    }
]
